{"name":"Break Curse","author":"CrusaderDroid","tier":3,"tags":["Abjuration","Holy"],"cost":"2 AP","range":"30 feet","duration":"Instantaneous","desc":"You immediately end any curse or Unholy spell affecting the target creature or object. A reanimated creature can make a saving throw using its caster's spellcasting stat to resist the effect. If the reanimated creature has more hit dice than you, and it would otherwise die if the spell ends, it instead takes 5d12 damage on a failed saving throw.","empower":""}