{"name": "Burst Gale","tier": 2, "tags": ["Evocation","Wind"], "cost": "2 AP","range": "60 feet","duration": "Instantaneous","desc": "Sudden strong winds burst out in a 5 foot wide, 15 foot long line starting at any point in range that you can see and traveling in any direction. Creatures in the way must make a Strength saving throw or take 4d6 bludgeoning damage and be thrown 20 feet in the direction of the wind. A creature that collides with another creature or object during this movement deals 2d6 damage to itself and the source of collision. A creature that succeeds on its saving throw takes half damage and does not move.","empower": "Line length increased to 25 feet.","author": "CrusaderDroid"}