{"name":"Gravechill","author":"CrusaderDroid","tier":5,"tags":["Necromancy","Cold"],"cost":"2 AP","range":"Touch","duration":"1 minute","desc":"The touched creature must succeed on a Constitution saving throw or be overtaken by a chill that grips their very soul. They take 6d10 cold damage, can't regain hit points or gain temporary hit points, and take 5 cold damage per 5 feet they move on their turn. A successful saving throw deals half damage and no other effect. The creature can repeat the saving throw at the end of each of their turns, ending the effect early on a success.<br><br>A creature that is reduced to 0 hit points while affected by this spell has their body freeze where it stands, preserving it in good condition. If a spell would reanimate this creature, it refunds MP equal to its tier to its caster.<br><br>If you are controlling a reanimated creature, you can have them deliver this spell with a touch instead of you.","empower":"Initial damage increased to 9d10."}